bq_nb_lib/__init__.py
bq_nb_lib/alert_ops.py
bq_nb_lib/logger_init.py
bq_nb_lib/mixpanel_handler.py
bq_nb_lib/s3_handler.py
bq_nb_lib/secret_manager.py
bq_nb_lib/slack_alert.py
bq_nb_lib/testtt.py
bq_nb_lib-0.1.5.dist-info/METADATA
bq_nb_lib-0.1.5.dist-info/WHEEL
bq_nb_lib-0.1.5.dist-info/top_level.txt
bq_nb_lib-0.1.5.dist-info/RECORD
