Metadata-Version: 2.1
Name: bq-nb-lib
Version: 0.1.5
Summary: A utility package for managing S3, Slack, and AlertOps integrations.
Home-page: UNKNOWN
Author: Rashed
Author-email: Rashed@terdac.com
License: UNKNOWN
Platform: UNKNOWN
Classifier: Programming Language :: Python :: 3
Classifier: License :: OSI Approved :: MIT License
Classifier: Operating System :: OS Independent
Requires-Python: >=3.7
Requires-Dist: requests
Requires-Dist: google-cloud-secret-manager
Requires-Dist: boto3
